LatLon/__init__.py
LatLon/lat_lon.py
LatLon-1.0.1.dist-info/DESCRIPTION.rst
LatLon-1.0.1.dist-info/METADATA
LatLon-1.0.1.dist-info/metadata.json
LatLon-1.0.1.dist-info/RECORD
LatLon-1.0.1.dist-info/top_level.txt
LatLon-1.0.1.dist-info/WHEEL
